{
    "class":"Класс",
    "race":"Раса",
    "level":"Уровень",
    "speed":"Скорость",
    "experience":"Опыт",
    "worldview":"Мировоззрение",
    "alingment":"Мировоззрение",
    "background":"Прошлое",
    "masterBonus":"Бонус Мастерства",
    "Strength":"Сила",
    "Dexterity":"Ловкость",
    "Constitution":"Телосложение",
    "Intelligence":"Интеллект",
    "Charisma":"Харизма",
    "Wisdom":"Мудрость",
    "MaxspellCells":"Максимальное количество магических ячеек",
    "Известные заговоры":"Известные заговоры",
    "Известные воззвания":"Известные воззвания",
    "Уровень ячеек":"Уровень ячеек",
    "Ячейки заклинаний":"Ячейки заклинаний",
    "1":"1",
    "2":"2",
    "3":"3",
    "4":"4",
    "5":"5",
    "6":"6",
    "7":"7",
    "8":"8",
    "9":"9",
    "Известные заклинания":"Известные заклинания"

    


    }
